pushover.py
pushover_simple_cli-1.1.2.dist-info/AUTHORS.rst
pushover_simple_cli-1.1.2.dist-info/LICENSE
pushover_simple_cli-1.1.2.dist-info/METADATA
pushover_simple_cli-1.1.2.dist-info/WHEEL
pushover_simple_cli-1.1.2.dist-info/entry_points.txt
pushover_simple_cli-1.1.2.dist-info/top_level.txt
pushover_simple_cli-1.1.2.dist-info/RECORD
