Metadata-Version: 2.1
Name: pushover-simple-cli
Version: 1.1.2
Summary: Send quick notifications to pushover
Home-page: https://github.com/alexrudy/pushover
Author: Alex Rudy
Author-email: pushover@alexrudy.net
License: BSD license
Keywords: pushover
Platform: UNKNOWN
Classifier: Development Status :: 5 - Production/Stable
Classifier: Intended Audience :: Developers
Classifier: License :: OSI Approved :: BSD License
Classifier: Natural Language :: English
Classifier: Programming Language :: Python :: 3
Classifier: Programming Language :: Python :: 3.5
Classifier: Programming Language :: Python :: 3.6
Classifier: Programming Language :: Python :: 3.7
Classifier: Programming Language :: Python :: 3.8
Requires-Python: !=3.0.*,!=3.1.*,!=3.2.*,!=3.3.*,!=3.4.*,>=2.7
License-File: LICENSE
License-File: AUTHORS.rst
Requires-Dist: Click (>=7.0)
Requires-Dist: requests
